LICENSE
MANIFEST.in
README.md
setup.py
ueberzug/__init__.py
ueberzug/__main__.py
ueberzug/action.py
ueberzug/batch.py
ueberzug/conversion.py
ueberzug/files.py
ueberzug/geometry.py
ueberzug/layer.py
ueberzug/library.py
ueberzug/loading.py
ueberzug/parser.py
ueberzug/pattern.py
ueberzug/process.py
ueberzug/query_windows.py
ueberzug/scaling.py
ueberzug/terminal.py
ueberzug/thread.py
ueberzug/tmux_util.py
ueberzug/ui.py
ueberzug/version.py
ueberzug/xutil.py
ueberzug/X/X.c
ueberzug/X/X.h
ueberzug/X/Xshm.c
ueberzug/X/Xshm.h
ueberzug/X/display.c
ueberzug/X/display.h
ueberzug/X/math.h
ueberzug/X/python.h
ueberzug/X/util.h
ueberzug/X/window.c
ueberzug/X/window.h
ueberzug/lib/__init__.py
ueberzug/lib/lib.sh
ueberzug/lib/v0/__init__.py
ueberzug_bak.egg-info/PKG-INFO
ueberzug_bak.egg-info/SOURCES.txt
ueberzug_bak.egg-info/dependency_links.txt
ueberzug_bak.egg-info/entry_points.txt
ueberzug_bak.egg-info/requires.txt
ueberzug_bak.egg-info/top_level.txt